LICENSE.md
MANIFEST.in
README.rst
requirements.txt
setup.py
docs/Makefile
docs/auth.rst
docs/celery.rst
docs/conf.py
docs/index.rst
docs/installation.rst
docs/make.bat
docs/management.rst
docs/plugins.rst
docs/plugins_frontend.rst
docs/settings.rst
docs/tags.rst
docs/themes.rst
docs/_build/doctrees/auth.doctree
docs/_build/doctrees/celery.doctree
docs/_build/doctrees/devenv.doctree
docs/_build/doctrees/environment.pickle
docs/_build/doctrees/index.doctree
docs/_build/doctrees/installation.doctree
docs/_build/doctrees/management.doctree
docs/_build/doctrees/plugins.doctree
docs/_build/doctrees/plugins_frontend.doctree
docs/_build/doctrees/server.doctree
docs/_build/doctrees/settings.doctree
docs/_build/doctrees/tags.doctree
docs/_build/doctrees/themes.doctree
docs/_build/html/.buildinfo
docs/_build/html/auth.html
docs/_build/html/celery.html
docs/_build/html/devenv.html
docs/_build/html/genindex.html
docs/_build/html/index.html
docs/_build/html/installation.html
docs/_build/html/management.html
docs/_build/html/objects.inv
docs/_build/html/plugins.html
docs/_build/html/plugins_frontend.html
docs/_build/html/search.html
docs/_build/html/searchindex.js
docs/_build/html/server.html
docs/_build/html/settings.html
docs/_build/html/tags.html
docs/_build/html/themes.html
docs/_build/html/_sources/auth.txt
docs/_build/html/_sources/celery.txt
docs/_build/html/_sources/devenv.txt
docs/_build/html/_sources/index.txt
docs/_build/html/_sources/installation.txt
docs/_build/html/_sources/management.txt
docs/_build/html/_sources/plugins.txt
docs/_build/html/_sources/plugins_frontend.txt
docs/_build/html/_sources/server.txt
docs/_build/html/_sources/settings.txt
docs/_build/html/_sources/tags.txt
docs/_build/html/_sources/themes.txt
docs/_build/html/_static/agogo.css
docs/_build/html/_static/ajax-loader.gif
docs/_build/html/_static/alert_info_32.png
docs/_build/html/_static/alert_warning_32.png
docs/_build/html/_static/basic.css
docs/_build/html/_static/bg-page.png
goscalecms.egg-info/PKG-INFO
goscalecms.egg-info/SOURCES.txt
goscalecms.egg-info/dependency_links.txt
goscalecms.egg-info/requires.txt
goscalecms.egg-info/top_level.txt