Metadata-Version: 1.1
Name: goscalecms
Version: 0.5.6
Summary: GoScale CMS
Home-page: https://github.com/sternoru/goscalecms
Author: Evgeny Demchenko
Author-email: little_pea@list.ru
License: BSD
Keywords: goscale cms django themes content management system mashup google ajax
Platform: UNKNOWN
Classifier: Development Status :: 3 - Alpha
Classifier: Topic :: Internet :: WWW/HTTP :: Site Management
Classifier: Environment :: Web Environment
Classifier: Framework :: Django
Classifier: Intended Audience :: Developers
Classifier: Natural Language :: English
Classifier: Natural Language :: French
Classifier: Natural Language :: Russian
Classifier: Programming Language :: Python
Classifier: Programming Language :: JavaScript
Classifier: License :: OSI Approved :: BSD License
